{
  "match_info": {
    "timestamp": "2020-09-28 02:45:00",
    "score": "2 - 2",
    "home_team": "AS Roma",
    "away_team": "Juventus",
    "home_formation": "3 - 4 - 2 - 1",
    "away_formation": "3 - 4 - 1 - 2",
    "venue": "Stadio Olimpico (Rome)",
    "capacity": "70 634",
    "attendance": "1 000"
  },
  "referee_data": {
    "short_name_country": "Di Bello M. (Ita)",
    "first_name": "Di Bello",
    "abbr_last_name": "M",
    "country": "Ita",
    "detected_name": "Marco Di Bello"
  },
  "players_data": {
    "home_coaches": [
      {
        "players_name": "Fonseca P.",
        "players_number": "",
        "Full Name": "Paulo Fonseca",
        "players_rating": "",
        "Country": "Portugal",
        "Role": "coach",
        "Age and Birthdate": "50,  (05.03.1973)",
        "Market Value": "",
        "unicode": "KAwSWnoE"
      }
    ],
    "home_missing_players": [
      {
        "players_name": "Pastore J.",
        "players_number": "",
        "Full Name": "Javier Pastore",
        "players_rating": "",
        "Country": "Argentina",
        "Role": "Midfielder",
        "Age and Birthdate": "34, (20.06.1989)",
        "Market Value": "",
        "unicode": "zJQlpJzt"
      },
      {
        "players_name": "Perotti D.",
        "players_number": "",
        "Full Name": "Diego Perotti",
        "players_rating": "",
        "Country": "Argentina",
        "Role": "Forward",
        "Age and Birthdate": "35, (26.07.1988)",
        "Market Value": "",
        "unicode": "Wx8pbtnB"
      },
      {
        "players_name": "Zaniolo N.",
        "players_number": "",
        "Full Name": "Nicolo Zaniolo",
        "players_rating": "",
        "Country": "Italy",
        "Role": "Midfielder",
        "Age and Birthdate": "24, (02.07.1999)",
        "Market Value": "€23.8m",
        "unicode": "0G7MtHBl"
      }
    ],
    "home_starting_lineups": [
      {
        "players_name": "Dzeko E. (C)",
        "players_number": "9",
        "Full Name": "Edin Dzeko",
        "players_rating": 7.3,
        "Country": "Bosnia and Herzegovina",
        "Role": "Forward",
        "Age and Birthdate": "37, (17.03.1986)",
        "Market Value": "€3.6m",
        "unicode": "zilGmgZq"
      },
      {
        "players_name": "Ibanez",
        "players_number": "3",
        "Full Name": "Ibanez",
        "players_rating": 7.1,
        "Country": "Brazil",
        "Role": "Defender",
        "Age and Birthdate": "25, (23.11.1998)",
        "Market Value": "€23.8m",
        "unicode": "tARMiREs"
      },
      {
        "players_name": "Kumbulla M.",
        "players_number": "24",
        "Full Name": "Marash Kumbulla",
        "players_rating": 6.7,
        "Country": "Albania",
        "Role": "Defender",
        "Age and Birthdate": "23, (08.02.2000)",
        "Market Value": "€7.1m",
        "unicode": "8xTCtgln"
      },
      {
        "players_name": "Mancini G.",
        "players_number": "23",
        "Full Name": "Gianluca Mancini",
        "players_rating": 6.3,
        "Country": "Italy",
        "Role": "Defender",
        "Age and Birthdate": "27, (17.04.1996)",
        "Market Value": "€19.6m",
        "unicode": "dMy1KKlG"
      },
      {
        "players_name": "Mirante A. (G)",
        "players_number": "83",
        "Full Name": "Antonio Mirante",
        "players_rating": 6.7,
        "Country": "Italy",
        "Role": "Goalkeeper",
        "Age and Birthdate": "40, (08.07.1983)",
        "Market Value": "€95k",
        "unicode": "2u1zBSC4"
      },
      {
        "players_name": "Mkhitaryan H.",
        "players_number": "77",
        "Full Name": "Henrikh Mkhitaryan",
        "players_rating": 7.5,
        "Country": "Armenia",
        "Role": "Midfielder",
        "Age and Birthdate": "34, (21.01.1989)",
        "Market Value": "€6.3m",
        "unicode": "KKi1DwHC"
      },
      {
        "players_name": "Pedro",
        "players_number": "11",
        "Full Name": "Pedro",
        "players_rating": 7.0,
        "Country": "Spain",
        "Role": "Midfielder",
        "Age and Birthdate": "36, (28.07.1987)",
        "Market Value": "€1.3m",
        "unicode": "0f1tMqQl"
      },
      {
        "players_name": "Pellegrini Lo.",
        "players_number": "7",
        "Full Name": "Lorenzo Pellegrini",
        "players_rating": 6.6,
        "Country": "Italy",
        "Role": "Midfielder",
        "Age and Birthdate": "27, (19.06.1996)",
        "Market Value": "€24.8m",
        "unicode": "8GVcLWJk"
      },
      {
        "players_name": "Santon D.",
        "players_number": "18",
        "Full Name": "Davide Santon",
        "players_rating": 6.8,
        "Country": "Italy",
        "Role": "Defender",
        "Age and Birthdate": "33, (02.01.1991)",
        "Market Value": "",
        "unicode": "8xvtP9Ll"
      },
      {
        "players_name": "Spinazzola L.",
        "players_number": "37",
        "Full Name": "Leonardo Spinazzola",
        "players_rating": 7.1,
        "Country": "Italy",
        "Role": "Defender",
        "Age and Birthdate": "30, (25.03.1993)",
        "Market Value": "€7.1m",
        "unicode": "UgYYWt1i"
      },
      {
        "players_name": "Veretout J.",
        "players_number": "17",
        "Full Name": "Jordan Veretout",
        "players_rating": 8.2,
        "Country": "France",
        "Role": "Midfielder",
        "Age and Birthdate": "30, (01.03.1993)",
        "Market Value": "€14.3m",
        "unicode": "88twBgtc"
      }
    ],
    "home_substituted_players": [
      {
        "players_name": "Bruno Peres",
        "players_number": "33",
        "Full Name": "Bruno Peres",
        "players_rating": 6.4,
        "Country": "Brazil",
        "Role": "Defender",
        "Age and Birthdate": "€726k, (01.03.1990)",
        "Market Value": "",
        "unicode": "GY0h7VoN"
      },
      {
        "players_name": "Diawara A.",
        "players_number": "42",
        "Full Name": "Amadou Diawara",
        "players_rating": 6.3,
        "Country": "Guinea",
        "Role": "Midfielder",
        "Age and Birthdate": "26, (17.07.1997)",
        "Market Value": "€1.7m",
        "unicode": "2Hs3xiw6"
      }
    ],
    "home_substitutes": [
      {
        "players_name": "Antonucci M.",
        "players_number": "48",
        "Full Name": "Mirko Antonucci",
        "players_rating": "",
        "Country": "Italy",
        "Role": "Forward",
        "Age and Birthdate": "24, (11.03.1999)",
        "Market Value": "€1.6m",
        "unicode": "ADBJ4OrH"
      },
      {
        "players_name": "Boer P. (G)",
        "players_number": "63",
        "Full Name": "Pietro Boer",
        "players_rating": "",
        "Country": "Italy",
        "Role": "Goalkeeper",
        "Age and Birthdate": "21, (12.05.2002)",
        "Market Value": "30.06.2024",
        "unicode": "0WLKioEG"
      },
      {
        "players_name": "Calafiori R.",
        "players_number": "61",
        "Full Name": "Riccardo Calafiori",
        "players_rating": "",
        "Country": "Italy",
        "Role": "Defender",
        "Age and Birthdate": "21, (19.05.2002)",
        "Market Value": "€12.4m",
        "unicode": "CEwq7x7l"
      },
      {
        "players_name": "Cristante B.",
        "players_number": "4",
        "Full Name": "Bryan Cristante",
        "players_rating": "",
        "Country": "Italy",
        "Role": "Midfielder",
        "Age and Birthdate": "28, (03.03.1995)",
        "Market Value": "€19.6m",
        "unicode": "t6u0o3h7"
      },
      {
        "players_name": "Kluivert J.",
        "players_number": "99",
        "Full Name": "Justin Kluivert",
        "players_rating": "",
        "Country": "Netherlands",
        "Role": "Forward",
        "Age and Birthdate": "24, (05.05.1999)",
        "Market Value": "€10.5m",
        "unicode": "fq4lU5sI"
      },
      {
        "players_name": "Lopez P. (G)",
        "players_number": "13",
        "Full Name": "Pau Lopez",
        "players_rating": "",
        "Country": "Spain",
        "Role": "Goalkeeper",
        "Age and Birthdate": "29, (13.12.1994)",
        "Market Value": "€11.7m",
        "unicode": "rZes9CKA"
      },
      {
        "players_name": "Perez C.",
        "players_number": "31",
        "Full Name": "Carles Perez",
        "players_rating": "",
        "Country": "Spain",
        "Role": "Forward",
        "Age and Birthdate": "25, (16.02.1998)",
        "Market Value": "€3.7m",
        "unicode": "0WJHh4Qs"
      },
      {
        "players_name": "Villar G.",
        "players_number": "14",
        "Full Name": "Gonzalo Villar",
        "players_rating": "",
        "Country": "Spain",
        "Role": "Midfielder",
        "Age and Birthdate": "25, (23.03.1998)",
        "Market Value": "€2.6m",
        "unicode": "QZtXmJ94"
      }
    ],
    "away_coaches": [
      {
        "players_name": "Pirlo A.",
        "players_number": "",
        "Full Name": "Andrea Pirlo",
        "players_rating": "",
        "Country": "Italy",
        "Role": "coach",
        "Age and Birthdate": "44,  (19.05.1979)",
        "Market Value": "",
        "unicode": "2kfSDavF"
      }
    ],
    "away_missing_players": [
      {
        "players_name": "Alex Sandro",
        "players_number": "",
        "Full Name": "Alex Sandro",
        "players_rating": "",
        "Country": "Brazil",
        "Role": "Defender",
        "Age and Birthdate": "32, (26.01.1991)",
        "Market Value": "€2.0m",
        "unicode": "hrkni8NN"
      },
      {
        "players_name": "Bernardeschi F.",
        "players_number": "",
        "Full Name": "Federico Bernardeschi",
        "players_rating": "",
        "Country": "Italy",
        "Role": "Forward",
        "Age and Birthdate": "29, (16.02.1994)",
        "Market Value": "",
        "unicode": "Ghmdi8ej"
      },
      {
        "players_name": "de Ligt M.",
        "players_number": "",
        "Full Name": "Matthijs de Ligt",
        "players_rating": "",
        "Country": "Netherlands",
        "Role": "Defender",
        "Age and Birthdate": "24, (12.08.1999)",
        "Market Value": "€62.7m",
        "unicode": "hhRKVBXN"
      },
      {
        "players_name": "Khedira S.",
        "players_number": "",
        "Full Name": "Sami Khedira",
        "players_rating": "",
        "Country": "Germany",
        "Role": "Midfielder",
        "Age and Birthdate": "36, (04.04.1987)",
        "Market Value": "",
        "unicode": "0AgmLAwr"
      }
    ],
    "away_starting_lineups": [
      {
        "players_name": "Bonucci L.",
        "players_number": "19",
        "Full Name": "Leonardo Bonucci",
        "players_rating": 6.8,
        "Country": "Italy",
        "Role": "Defender",
        "Age and Birthdate": "36, (01.05.1987)",
        "Market Value": "€1.4m",
        "unicode": "zmOGDSwg"
      },
      {
        "players_name": "Chiellini G. (C)",
        "players_number": "3",
        "Full Name": "Giorgio Chiellini",
        "players_rating": 7.2,
        "Country": "Italy",
        "Role": "Defender",
        "Age and Birthdate": "39, (14.08.1984)",
        "Market Value": "",
        "unicode": "K2KuC4Uu"
      },
      {
        "players_name": "Cuadrado J.",
        "players_number": "16",
        "Full Name": "Juan Cuadrado",
        "players_rating": 7.3,
        "Country": "Colombia",
        "Role": "Defender",
        "Age and Birthdate": "35, (26.05.1988)",
        "Market Value": "€2.0m",
        "unicode": "AFefBpwI"
      },
      {
        "players_name": "Danilo",
        "players_number": "13",
        "Full Name": "Danilo",
        "players_rating": 8.2,
        "Country": "Brazil",
        "Role": "Defender",
        "Age and Birthdate": "32, (15.07.1991)",
        "Market Value": "€11.9m",
        "unicode": "KUjvgUhB"
      },
      {
        "players_name": "Kulusevski D.",
        "players_number": "44",
        "Full Name": "Dejan Kulusevski",
        "players_rating": 7.1,
        "Country": "Sweden",
        "Role": "Forward",
        "Age and Birthdate": "23, (25.04.2000)",
        "Market Value": "€54.6m",
        "unicode": "fXLqHCYi"
      },
      {
        "players_name": "McKennie W.",
        "players_number": "14",
        "Full Name": "Weston McKennie",
        "players_rating": 6.4,
        "Country": "USA",
        "Role": "Midfielder",
        "Age and Birthdate": "25, (28.08.1998)",
        "Market Value": "€22.8m",
        "unicode": "jZHxRi2A"
      },
      {
        "players_name": "Morata A.",
        "players_number": "9",
        "Full Name": "Alvaro Morata",
        "players_rating": 7.0,
        "Country": "Spain",
        "Role": "Forward",
        "Age and Birthdate": "31, (23.10.1992)",
        "Market Value": "€19.6m",
        "unicode": "fmkHs3aU"
      },
      {
        "players_name": "Rabiot A.",
        "players_number": "25",
        "Full Name": "Adrien Rabiot",
        "players_rating": 4.7,
        "Country": "France",
        "Role": "Midfielder",
        "Age and Birthdate": "28, (03.04.1995)",
        "Market Value": "€40.3m",
        "unicode": "l08EAP2Q"
      },
      {
        "players_name": "Ramsey A.",
        "players_number": "8",
        "Full Name": "Aaron Ramsey",
        "players_rating": 6.6,
        "Country": "Wales",
        "Role": "Midfielder",
        "Age and Birthdate": "33, (26.12.1990)",
        "Market Value": "€1.4m",
        "unicode": "fBD08Fin"
      },
      {
        "players_name": "Ronaldo C.",
        "players_number": "7",
        "Full Name": "Cristiano Ronaldo",
        "players_rating": 7.7,
        "Country": "Portugal",
        "Role": "Forward",
        "Age and Birthdate": "38, (05.02.1985)",
        "Market Value": "€15.7m",
        "unicode": "WGOY4FSt"
      },
      {
        "players_name": "Szczesny W. (G)",
        "players_number": "1",
        "Full Name": "Wojciech Szczesny",
        "players_rating": 7.3,
        "Country": "Poland",
        "Role": "Goalkeeper",
        "Age and Birthdate": "33, (18.04.1990)",
        "Market Value": "€8.4m",
        "unicode": "6NtwHZ7F"
      }
    ],
    "away_substituted_players": [
      {
        "players_name": "Arthur Melo",
        "players_number": "5",
        "Full Name": "Arthur Melo",
        "players_rating": 6.8,
        "Country": "Brazil",
        "Role": "Midfielder",
        "Age and Birthdate": "27, (12.08.1996)",
        "Market Value": "€14.0m",
        "unicode": "UaXWh1Wj"
      },
      {
        "players_name": "Bentancur R.",
        "players_number": "30",
        "Full Name": "Rodrigo Bentancur",
        "players_rating": 6.5,
        "Country": "Uruguay",
        "Role": "Midfielder",
        "Age and Birthdate": "26, (25.06.1997)",
        "Market Value": "€34.7m",
        "unicode": "nLRMnJtJ"
      },
      {
        "players_name": "Costa D.",
        "players_number": "11",
        "Full Name": "Douglas Costa",
        "players_rating": 6.6,
        "Country": "Brazil",
        "Role": "Midfielder",
        "Age and Birthdate": "€1.5m, (14.09.1990)",
        "Market Value": "",
        "unicode": "fPOJMEfo"
      },
      {
        "players_name": "Frabotta G.",
        "players_number": "38",
        "Full Name": "Gianluca Frabotta",
        "players_rating": "",
        "Country": "Italy",
        "Role": "Defender",
        "Age and Birthdate": "24, (24.06.1999)",
        "Market Value": "€936k",
        "unicode": "f9y3on9q"
      }
    ],
    "away_substitutes": [
      {
        "players_name": "Buffon G. (G)",
        "players_number": "77",
        "Full Name": "Gianluigi Buffon",
        "players_rating": "",
        "Country": "Italy",
        "Role": "Goalkeeper",
        "Age and Birthdate": "30.06.2024, (28.01.1978)",
        "Market Value": "",
        "unicode": "xKQMi1qO"
      },
      {
        "players_name": "De Sciglio M.",
        "players_number": "2",
        "Full Name": "Mattia De Sciglio",
        "players_rating": "",
        "Country": "Italy",
        "Role": "Defender",
        "Age and Birthdate": "31, (20.10.1992)",
        "Market Value": "€1.9m",
        "unicode": "Ua5srQK6"
      },
      {
        "players_name": "Demiral M.",
        "players_number": "28",
        "Full Name": "Merih Demiral",
        "players_rating": "",
        "Country": "Turkey",
        "Role": "Defender",
        "Age and Birthdate": "25, (05.03.1998)",
        "Market Value": "€17.4m",
        "unicode": "MRw4A5FO"
      },
      {
        "players_name": "Dybala P.",
        "players_number": "10",
        "Full Name": "Paulo Dybala",
        "players_rating": "",
        "Country": "Argentina",
        "Role": "Forward",
        "Age and Birthdate": "30, (15.11.1993)",
        "Market Value": "€24.8m",
        "unicode": "W4myUVXR"
      },
      {
        "players_name": "Pinsoglio C. (G)",
        "players_number": "31",
        "Full Name": "Carlo Pinsoglio",
        "players_rating": "",
        "Country": "Italy",
        "Role": "Goalkeeper",
        "Age and Birthdate": "33, (16.03.1990)",
        "Market Value": "30.06.2025",
        "unicode": "Uii1AJuK"
      },
      {
        "players_name": "Portanova M.",
        "players_number": "39",
        "Full Name": "Manolo Portanova",
        "players_rating": "",
        "Country": "Italy",
        "Role": "Midfielder",
        "Age and Birthdate": "23, (02.06.2000)",
        "Market Value": "€397k",
        "unicode": "AwsyawQ1"
      },
      {
        "players_name": "Rugani D.",
        "players_number": "24",
        "Full Name": "Daniele Rugani",
        "players_rating": "",
        "Country": "Italy",
        "Role": "Defender",
        "Age and Birthdate": "29, (29.07.1994)",
        "Market Value": "€4.0m",
        "unicode": "zyoOMhpU"
      },
      {
        "players_name": "Vrioni G.",
        "players_number": "40",
        "Full Name": "Giacomo Vrioni",
        "players_rating": "",
        "Country": "Albania",
        "Role": "Forward",
        "Age and Birthdate": "25, (15.10.1998)",
        "Market Value": "€2.4m",
        "unicode": "AeAZMqTq"
      }
    ]
  },
  "comments": [
    {
      "half": 1,
      "time_stamp": "08:03",
      "comments_type": "goal",
      "comments_text": "The defence had a hard time blocking out the strike from Cristiano Ronaldo (Juventus). He didn't hesitate and finished from outside the box right after he had received a pass from his teammate.",
      "comments_text_anonymized": "The defence had a hard time blocking out the strike from [PLAYER] ([TEAM]). He didn't hesitate and finished from outside the box right after he had received a pass from his teammate.",
      "index": 0
    },
    {
      "half": 1,
      "time_stamp": "09:42",
      "comments_type": "corner",
      "comments_text": "AS Roma take a short corner instead of sending the ball into the penalty area.",
      "comments_text_anonymized": "[TEAM] take a short corner instead of sending the ball into the penalty area.",
      "index": 1
    },
    {
      "half": 1,
      "time_stamp": "20:59",
      "comments_type": "corner",
      "comments_text": "Dejan Kulusevski (Juventus) works the corner short instead of sending the ball into the penalty area.",
      "comments_text_anonymized": "[PLAYER] ([TEAM]) works the corner short instead of sending the ball into the penalty area.",
      "index": 2
    },
    {
      "half": 1,
      "time_stamp": "21:05",
      "comments_type": "corner",
      "comments_text": "The resulting corner from Dejan Kulusevski (Juventus) is cleared by the defence.",
      "comments_text_anonymized": "The resulting corner from [PLAYER] ([TEAM]) is cleared by the defence.",
      "index": 3
    },
    {
      "half": 1,
      "time_stamp": "21:55",
      "comments_type": "corner",
      "comments_text": "Dejan Kulusevski (Juventus) takes the corner, but it's intercepted by the defender.",
      "comments_text_anonymized": "[PLAYER] ([TEAM]) takes the corner, but it's intercepted by the defender.",
      "index": 4
    },
    {
      "half": 1,
      "time_stamp": "22:35",
      "comments_type": "corner",
      "comments_text": "Dejan Kulusevski (Juventus) will deliver the corner kick.",
      "comments_text_anonymized": "[PLAYER] ([TEAM]) will deliver the corner kick.",
      "index": 5
    },
    {
      "half": 1,
      "time_stamp": "29:56",
      "comments_type": "yellow card",
      "comments_text": "The yellow card is received by Adrien Rabiot (Juventus).",
      "comments_text_anonymized": "The yellow card is received by [PLAYER] ([TEAM]).",
      "index": 6
    },
    {
      "half": 1,
      "time_stamp": "30:57",
      "comments_type": "goal",
      "comments_text": "Goal! Wojciech Szczesny gets a hand on the penalty from Jordan Veretout (AS Roma), but can't stop it from flying into the bottom left corner.",
      "comments_text_anonymized": "Goal! [PLAYER] gets a hand on the penalty from [PLAYER] ([TEAM]), but can't stop it from flying into the bottom left corner.",
      "index": 7
    },
    {
      "half": 1,
      "time_stamp": "35:24",
      "comments_type": "yellow card",
      "comments_text": "Marco Di Bello shows a yellow card to Marash Kumbulla (AS Roma) for his blatant foul.",
      "comments_text_anonymized": "[REFEREE] shows a yellow card to [PLAYER] ([TEAM]) for his blatant foul.",
      "index": 8
    },
    {
      "half": 1,
      "time_stamp": "42:54",
      "comments_type": "penalty",
      "comments_text": "Cristiano Ronaldo (Juventus) is going to take the penalty!",
      "comments_text_anonymized": "[PLAYER] ([TEAM]) is going to take the penalty!",
      "index": 9
    },
    {
      "half": 1,
      "time_stamp": "42:56",
      "comments_type": "goal",
      "comments_text": "Goal! Cristiano Ronaldo (Juventus) wins the battle of wills and sends an unstoppable penalty past Antonio Mirante into the bottom right corner.",
      "comments_text_anonymized": "Goal! [PLAYER] ([TEAM]) wins the battle of wills and sends an unstoppable penalty past [PLAYER] into the bottom right corner.",
      "index": 10
    },
    {
      "half": 1,
      "time_stamp": "45:58",
      "comments_type": "goal",
      "comments_text": "Goal! Jordan Veretout (AS Roma) beautifully controls a strongly hit pass from Henrikh Mkhitaryan inside the box. He cuts inside his marker and rifles the ball into the bottom right corner. 2:1.",
      "comments_text_anonymized": "Goal! [PLAYER] ([TEAM]) beautifully controls a strongly hit pass from [PLAYER] inside the box. He cuts inside his marker and rifles the ball into the bottom right corner. 2:1.",
      "index": 11
    },
    {
      "half": 2,
      "time_stamp": "05:00",
      "comments_type": "corner",
      "comments_text": "AS Roma take a short corner kick.",
      "comments_text_anonymized": "[TEAM] take a short corner kick.",
      "index": 12
    },
    {
      "half": 2,
      "time_stamp": "05:24",
      "comments_type": "corner",
      "comments_text": "The referee awards a corner and Lorenzo Pellegrini (AS Roma) goes over to take it.",
      "comments_text_anonymized": "The referee awards a corner and [PLAYER] ([TEAM]) goes over to take it.",
      "index": 13
    },
    {
      "half": 2,
      "time_stamp": "08:40",
      "comments_type": "yellow card",
      "comments_text": "Lorenzo Pellegrini (AS Roma) is literally asking for a yellow card with his behaviour. The referee agrees and books him.",
      "comments_text_anonymized": "[PLAYER] ([TEAM]) is literally asking for a yellow card with his behaviour. The referee agrees and books him.",
      "index": 14
    },
    {
      "half": 2,
      "time_stamp": "12:38",
      "comments_type": "substitution",
      "comments_text": "Substitution. Alvaro Morata will be replaced by Douglas Costa (Juventus).",
      "comments_text_anonymized": "Substitution. [PLAYER] will be replaced by [PLAYER] ([TEAM]).",
      "index": 15
    },
    {
      "half": 2,
      "time_stamp": "12:49",
      "comments_type": "substitution",
      "comments_text": "Here is a change. Weston McKennie is going off and Andrea Pirlo gives the last tactical orders to Arthur (Juventus).",
      "comments_text_anonymized": "Here is a change. [PLAYER] is going off and [PLAYER] gives the last tactical orders to [PLAYER] ([TEAM]).",
      "index": 16
    },
    {
      "half": 2,
      "time_stamp": "16:36",
      "comments_type": "second yellow card",
      "comments_text": "Adrien Rabiot (Juventus) must have known he would be sent off for this foul, but he had to stop the opponent at all costs. Marco Di Bello shows him a second yellow card and the game has ended for him.",
      "comments_text_anonymized": "[PLAYER] ([TEAM]) must have known he would be sent off for this foul, but he had to stop the opponent at all costs. [REFEREE] shows him a second yellow card and the game has ended for him.",
      "index": 17
    },
    {
      "half": 2,
      "time_stamp": "22:36",
      "comments_type": "substitution",
      "comments_text": "It's time for a substitution. That's the last involvement from Aaron Ramsey as he is replaced by Rodrigo Bentancur (Juventus).",
      "comments_text_anonymized": "It's time for a substitution. That's the last involvement from [PLAYER] as he is replaced by [PLAYER] ([TEAM]).",
      "index": 18
    },
    {
      "half": 2,
      "time_stamp": "22:41",
      "comments_type": "substitution",
      "comments_text": "Paulo Fonseca has decided to make a change. Bruno Peres (AS Roma) replaces Davide Santon.",
      "comments_text_anonymized": "[PLAYER] has decided to make a change. [PLAYER] ([TEAM]) replaces [PLAYER].",
      "index": 19
    },
    {
      "half": 2,
      "time_stamp": "23:47",
      "comments_type": "goal",
      "comments_text": "Cristiano Ronaldo (Juventus) leaps to meet a beautiful cross and produces a header which goes low inside the left post.",
      "comments_text_anonymized": "[PLAYER] ([TEAM]) leaps to meet a beautiful cross and produces a header which goes low inside the left post.",
      "index": 20
    },
    {
      "half": 2,
      "time_stamp": "25:54",
      "comments_type": "substitution",
      "comments_text": "Here's the change. Lorenzo Pellegrini leaves the pitch and Amadou Diawara (AS Roma) comes on as a substitute.",
      "comments_text_anonymized": "Here's the change. [PLAYER] leaves the pitch and [PLAYER] ([TEAM]) comes on as a substitute.",
      "index": 21
    },
    {
      "half": 2,
      "time_stamp": "34:53",
      "comments_type": "corner",
      "comments_text": "Jordan Veretout (AS Roma) takes the corner kick but the ball only finds the head of an opponent.",
      "comments_text_anonymized": "[PLAYER] ([TEAM]) takes the corner kick but the ball only finds the head of an opponent.",
      "index": 22
    },
    {
      "half": 2,
      "time_stamp": "37:23",
      "comments_type": "corner",
      "comments_text": "The resulting corner from Jordan Veretout (AS Roma) is cleared.",
      "comments_text_anonymized": "The resulting corner from [PLAYER] ([TEAM]) is cleared.",
      "index": 23
    },
    {
      "half": 2,
      "time_stamp": "39:29",
      "comments_type": "substitution",
      "comments_text": "Substitution. Gianluca Frabotta (Juventus) in, Dejan Kulusevski out.",
      "comments_text_anonymized": "Substitution. [PLAYER] ([TEAM]) in, [PLAYER] out.",
      "index": 24
    },
    {
      "half": 2,
      "time_stamp": "40:36",
      "comments_type": "yellow card",
      "comments_text": "Gianluca Frabotta (Juventus) is rightly booked by the referee because it could not have been anything other than a yellow card.",
      "comments_text_anonymized": "[PLAYER] ([TEAM]) is rightly booked by the referee because it could not have been anything other than a yellow card.",
      "index": 25
    },
    {
      "half": 2,
      "time_stamp": "42:38",
      "comments_type": "corner",
      "comments_text": "Douglas Costa (Juventus) steps up to send the ball in.",
      "comments_text_anonymized": "[PLAYER] ([TEAM]) steps up to send the ball in.",
      "index": 26
    },
    {
      "half": 2,
      "time_stamp": "44:30",
      "comments_type": "corner",
      "comments_text": "Douglas Costa (Juventus) launches a powerful cross from the corner into the box, but the ball is intercepted by the defender.",
      "comments_text_anonymized": "[PLAYER] ([TEAM]) launches a powerful cross from the corner into the box, but the ball is intercepted by the defender.",
      "index": 27
    },
    {
      "half": 2,
      "time_stamp": "45:01",
      "comments_type": "corner",
      "comments_text": "The corner kick from Douglas Costa (Juventus) is headed out of the penalty area by one of the defenders.",
      "comments_text_anonymized": "The corner kick from [PLAYER] ([TEAM]) is headed out of the penalty area by one of the defenders.",
      "index": 28
    }
  ]
}